concurrent_assertions/file.sv
//--------------------------------------------------------------------------------------------
// Concurrent Assertions
//--------------------------------------------------------------------------------------------
module top;
  
  bit a,b; bit clk;
  always #10 clk = ~clk;
  initial 
    begin
      for(int i=0;i<10;i++)
        begin
          @(posedge clk);
          a <= $random; b <= $random;
          $display("[%0t] a=%0b,b=%0b", $time,a,b);
        end
      #10 $finish;
    end
  
  assert property (@(posedge clk) a & b);
    //assert property (@(posedge clk) a | b);
    initial 
      begin
        $dumpvars();
        $dumpfile("tb.vcd");
      end
    endmodule

concurrent_assertions/dump.vcd
$date
	Wed Oct 27 21:14:14 2021
$end
$version
	QuestaSim Version 10.6c
$end
$timescale
	1ns
$end

$scope module top $end
$var reg 1 ! a $end
$var reg 1 " b $end
$var reg 1 # clk $end
$upscope $end

$scope begin std $end
$upscope $end
$enddefinitions $end
#0
$dumpvars
0!
0"
0#
$end
#10
1#
1"
#20
0#
#30
1#
1!
#40
0#
#50
1#
#60
0#
#70
1#
0"
#80
0#
#90
1#
1"
#100
0#
#110
1#
0!
#120
0#
#130
1#
1!
0"
#140
0#
#150
1#
#160
0#
#170
1#
#180
0#
#190
1#
1"
