local_variables/file.sv
//--------------------------------------------------------------------------------------------
// Local_variables
//--------------------------------------------------------------------------------------------
module top;
  bit clk,a,b,c,e,f;
 
  //clock generation
  initial begin
    clk = 1'b0;
  forever #1 clk=!clk;
  end 
  
  //generating signals a,b,c,e,f
  initial begin
    repeat(2)
      forever
        begin
    a=1;b=1;c=1;e=1;f=1;
    #1 a=1;b=1;c=0;e=0;f=1;
            #1 a=0;b=1;c=0;e=1;f=0;
            #1 a=1;b=0;c=1;e=0;f=1;
            #1 a=1;b=1;c=1;e=1;f=1;
  end
  end

//assigning local variable in the property
  property data;
    bit x,y;
    @(posedge clk) (a ##1 b, x = e, y = x && f) ##1 c[*2];
  endproperty 

//checking assertion  
  assert property(data)
    else
      $error("out"); 
       initial begin
      $monitor("%t:a=%d,b=%d,c=%d,e=%d,f=%d",$time,a,b,c,e,f);
    #50 $finish;
  end
  initial begin
    $dumpvars();
    $dumpfile("top.vcd");
  end
  endmodule

local_variables/dump.vcd
$date
	Wed Oct 27 17:45:57 2021
$end
$version
	QuestaSim Version 10.6c
$end
$timescale
	1ns
$end

$scope module top $end
$var reg 1 ! clk $end
$var reg 1 " a $end
$var reg 1 # b $end
$var reg 1 $ c $end
$var reg 1 % e $end
$var reg 1 & f $end
$upscope $end

$scope begin std $end
$upscope $end
$enddefinitions $end
#0
$dumpvars
0!
1"
1#
1$
1%
1&
$end
#1
1!
0$
0%
#2
0!
0"
1%
0&
#3
1!
1"
0#
1$
0%
1&
#4
0!
1#
1%
#5
1!
0$
0%
#6
0!
0"
1%
0&
#7
1!
1"
0#
1$
0%
1&
#8
0!
1#
1%
#9
1!
0$
0%
#10
0!
0"
1%
0&
#11
1!
1"
0#
1$
0%
1&
#12
0!
1#
1%
#13
1!
0$
0%
#14
0!
0"
1%
0&
#15
1!
1"
0#
1$
0%
1&
#16
0!
1#
1%
#17
1!
0$
0%
#18
0!
0"
1%
0&
#19
1!
1"
0#
1$
0%
1&
#20
0!
1#
1%
#21
1!
0$
0%
#22
0!
0"
1%
0&
#23
1!
1"
0#
1$
0%
1&
#24
0!
1#
1%
#25
1!
0$
0%
#26
0!
0"
1%
0&
#27
1!
1"
0#
1$
0%
1&
#28
0!
1#
1%
#29
1!
0$
0%
#30
0!
0"
1%
0&
#31
1!
1"
0#
1$
0%
1&
#32
0!
1#
1%
#33
1!
0$
0%
#34
0!
0"
1%
0&
#35
1!
1"
0#
1$
0%
1&
#36
0!
1#
1%
#37
1!
0$
0%
#38
0!
0"
1%
0&
#39
1!
1"
0#
1$
0%
1&
#40
0!
1#
1%
#41
1!
0$
0%
#42
0!
0"
1%
0&
#43
1!
1"
0#
1$
0%
1&
#44
0!
1#
1%
#45
1!
0$
0%
#46
0!
0"
1%
0&
#47
1!
1"
0#
1$
0%
1&
#48
0!
1#
1%
#49
1!
0$
0%
