calling_subroutines/file.sv
//--------------------------------------------------------------------------------------------
// Calling_subroutines
//--------------------------------------------------------------------------------------------
module top;
  bit  clk,a,b,e,f;
  
    //clock generation
  initial begin
    clk = 1'b0;
  forever #1 clk=!clk;
  end 
  
    //generating signals
  initial begin
   repeat(2)
     forever
        begin
    a=1;b=1;e=1;f=1;
    #2 a=1;b=1;e=0;f=1;
            #2 a=1;b=1;e=1;f=0;
            #2 a=1;b=0;e=0;f=1;
            #2 a=1;b=1;e=1;f=0;
  end
  end
  
  //calling subroutine in sequence
  sequence s1;
logic v, w;
    @(posedge clk) (a, v = e) ##1
(b[->1], w = f, $display("b after a with v = %h, w = %h\n", v, w));
endsequence

  assert property(s1)
    else
      $error("out"); 
    
    initial begin
      $monitor("%t:a=%d,b=%d,e=%d,f=%d",$time,a,b,e,f);
      #50 $finish;
  end
  
  initial begin
    $dumpvars();
    $dumpfile("top.vcd");
  end
   
   endmodule

calling_subroutines/dump.vcd
$date
	Wed Oct 27 17:50:21 2021
$end
$version
	QuestaSim Version 10.6c
$end
$timescale
	1ns
$end

$scope module top $end
$var reg 1 ! clk $end
$var reg 1 " a $end
$var reg 1 # b $end
$var reg 1 $ e $end
$var reg 1 % f $end
$upscope $end

$scope begin std $end
$upscope $end
$enddefinitions $end
#0
$dumpvars
0!
1"
1#
1$
1%
$end
#1
1!
#2
0$
0!
#3
1!
#4
1$
0%
0!
#5
1!
#6
0#
0$
1%
0!
#7
1!
#8
1#
1$
0%
1%
0!
#9
1!
#10
0$
0!
#11
1!
#12
1$
0%
0!
#13
1!
#14
0#
0$
1%
0!
#15
1!
#16
1#
1$
0%
1%
0!
#17
1!
#18
0$
0!
#19
1!
#20
1$
0%
0!
#21
1!
#22
0#
0$
1%
0!
#23
1!
#24
1#
1$
0%
1%
0!
#25
1!
#26
0$
0!
#27
1!
#28
1$
0%
0!
#29
1!
#30
0#
0$
1%
0!
#31
1!
#32
1#
1$
0%
1%
0!
#33
1!
#34
0$
0!
#35
1!
#36
1$
0%
0!
#37
1!
#38
0#
0$
1%
0!
#39
1!
#40
1#
1$
0%
1%
0!
#41
1!
#42
0$
0!
#43
1!
#44
1$
0%
0!
#45
1!
#46
0#
0$
1%
0!
#47
1!
#48
1#
1$
0%
1%
0!
